{
  "self": "",
  "uri": "https://www.liveme.com/share/index_live.php?title=Chit+Chat+Chill%2FOlympics+%23FeatureMe&pic=http://live.store.cmcm.com/big/liveme/cover-622b334a3e3b90d639ce94d0e61bcefc_icon.jpeg&url=http%3A%2F%2Fwww.liveme.com%2Fmedia%2Fliveshort%2Fdist%2F%3Fvideoid%3D15182277923178718332%26area%3DA_US%26countryCode%3DUS%26topDown%3D1&kid=2&shareto=twitter&s=911061203571703808",
  "estimated-creation-date": "",
  "earliest-sources": [],
  "sources": {
    "bing.com": {
      "earliest": ""
    },
    "twitter.com": {
      "earliest": ""
    },
    "backlinks": {
      "earliest": ""
    },
    "pubdate": {
      "earliest": ""
    },
    "bitly.com": {
      "earliest": ""
    },
    "google.com": {
      "earliest": ""
    },
    "last-modified": {
      "earliest": ""
    }
  }
}
