{
  "self": "",
  "uri": "https://www.indieframe.com/media/74096",
  "estimated-creation-date": "2018-02-09T15:12:18",
  "earliest-sources": [
    "twitter.com"
  ],
  "sources": {
    "bing.com": {
      "earliest": ""
    },
    "twitter.com": {
      "earliest": "2018-02-09T15:12:18"
    },
    "backlinks": {
      "earliest": ""
    },
    "pubdate": {
      "earliest": ""
    },
    "bitly.com": {
      "earliest": ""
    },
    "google.com": {
      "earliest": ""
    },
    "last-modified": {
      "earliest": ""
    }
  }
}
